icarogw/__init__.py
icarogw/cosmologies.py
icarogw/injections.py
icarogw/posterior_samples.py
icarogw/analyses/__init__.py
icarogw/analyses/cosmo_pop_rate_marginalized.py
icarogw/priors/__init__.py
icarogw/priors/custom_bilby_priors.py
icarogw/priors/custom_math_priors.py
icarogw/priors/mass.py
icarogw/priors/redshift.py
icarogw/utils/__init__.py
icarogw/utils/conversions.py
icarogw/utils/plotting.py
icarogw/utils/quick_init.py
icarogw/utils/simulate.py
icarogw-1.0.5.dist-info/LICENSE
icarogw-1.0.5.dist-info/METADATA
icarogw-1.0.5.dist-info/WHEEL
icarogw-1.0.5.dist-info/top_level.txt
icarogw-1.0.5.dist-info/RECORD
