Metadata-Version: 2.1
Name: icarogw
Version: 1.0.5
Summary: A package for gravitational waves population inference
Home-page: UNKNOWN
Author: Simone Mastrogiovanni
Author-email: mastrogiovanni.simo@gmail.com
License: UNKNOWN
Platform: UNKNOWN
Classifier: Programming Language :: Python :: 3
Classifier: License :: OSI Approved :: MIT License
Classifier: Operating System :: OS Independent
Requires-Python: >=3.6
License-File: LICENSE
